jsdoc/__init__.py
jsdoc/models.py
jsdoc/parser.py
jsdoc-1.0.3.dist-info/METADATA
jsdoc-1.0.3.dist-info/WHEEL
jsdoc-1.0.3.dist-info/top_level.txt
jsdoc-1.0.3.dist-info/RECORD
