Metadata-Version: 2.4
Name: jsdoc
Version: 1.0.3
Summary: A Python package for parsing JSDoc comment blocks into structured BaseModel objects
Author-email: JSDoc Authors <authors@jsdoc.com>
License: MIT
Project-URL: Homepage, https://github.com/yunfanye/jsdoc
Project-URL: Documentation, https://github.com/yunfanye/jsdoc
Project-URL: Repository, https://github.com/yunfanye/jsdoc.git
Project-URL: Bug Tracker, https://github.com/yunfanye/jsdoc/issues
Keywords: jsdoc,documentation,parser,javascript
Classifier: Development Status :: 5 - Production/Stable
Classifier: Intended Audience :: Developers
Classifier: License :: OSI Approved :: MIT License
Classifier: Programming Language :: Python :: 3
Classifier: Programming Language :: Python :: 3.8
Classifier: Programming Language :: Python :: 3.9
Classifier: Programming Language :: Python :: 3.10
Classifier: Programming Language :: Python :: 3.11
Classifier: Programming Language :: Python :: 3.12
Classifier: Topic :: Software Development :: Documentation
Classifier: Topic :: Text Processing :: Markup
Requires-Python: >=3.8
Requires-Dist: pydantic>=2.0.0
Provides-Extra: dev
Requires-Dist: pytest>=6.0; extra == "dev"
Requires-Dist: pytest-cov; extra == "dev"
Requires-Dist: black; extra == "dev"
Requires-Dist: isort; extra == "dev"
Requires-Dist: flake8; extra == "dev"
